msiem/__init__.py
msiem/__main__.py
msiem/__pathutils__.py
msiem/__version__.py
msiem/cli.py
msiem/dstools.py
msiem-0.3.3.dist-info/LICENSE
msiem-0.3.3.dist-info/METADATA
msiem-0.3.3.dist-info/WHEEL
msiem-0.3.3.dist-info/entry_points.txt
msiem-0.3.3.dist-info/top_level.txt
msiem-0.3.3.dist-info/RECORD
