Metadata-Version: 2.1
Name: msiem
Version: 0.3.3
Summary: McAfee SIEM Command Line Interface
Home-page: https://github.com/mfesiem/msiem
Author: tristanlatr, andywalden
License: The MIT License
Platform: UNKNOWN
Classifier: Programming Language :: Python :: 3
Requires-Dist: msiempy
Requires-Dist: requests
Requires-Dist: lxml
